simple_model/__init__.py
simple_model/helpers.py
simple_model/v1/__init__.py
simple_model/v1/attribute.py
simple_model/v1/model.py
simple_model/v2/__init__.py
simple_model-1.3.0.post4.dist-info/METADATA
simple_model-1.3.0.post4.dist-info/RECORD
simple_model-1.3.0.post4.dist-info/WHEEL
simple_model-1.3.0.post4.dist-info/top_level.txt
