Metadata-Version: 2.1
Name: simple-model
Version: 1.3.0.post4
Summary: very simple model framework
Home-page: https://github.com/afriemann/simple_model
Author: Aljosha Friemann
Author-email: a.friemann@automate.wtf
License: UNKNOWN
Download-URL: https://github.com/afriemann/simple_model/archive/1.3.0.post4.tar.gz
Keywords: model,serialization,validation,dataclass
Platform: linux
Classifier: Programming Language :: Python :: 2.7
Classifier: Programming Language :: Python :: 3
Classifier: Operating System :: POSIX :: Linux
Classifier: Topic :: Software Development :: Libraries
Classifier: License :: OSI Approved :: BSD License
